mity/__init__.py
mity/mity.py
mity-0.0.1.dist-info/entry_points.txt
mity-0.0.1.dist-info/LICENSE
mity-0.0.1.dist-info/WHEEL
mity-0.0.1.dist-info/METADATA
mity-0.0.1.dist-info/RECORD
