Metadata-Version: 2.1
Name: mity
Version: 0.0.1
Summary: Mity: invoke orthogonal workflows from a single tool
Home-page: https://aikchar.me/blog/what-is-mity.html
License: UNKNOWN
Author: Hamza Sheikh
Author-email: code@codeghar.com
Requires-Python: ~=3.7
Classifier: License :: OSI Approved :: MIT License
Classifier: Programming Language :: Python :: 3
Requires-Dist: invoke
Requires-Dist: knack
Requires-Dist: pytest; extra == "test"
Requires-Dist: sphinx; extra == "doc"
Provides-Extra: .none
Provides-Extra: doc
Provides-Extra: test
